pytest_initry/__init__.py
pytest_initry/plugin.py
pytest_initry/protobufs/__init__.py
pytest_initry/protobufs/responses_pb2.py
pytest_initry/protobufs/responses_pb2.pyi
pytest_initry/protobufs/responses_pb2_grpc.py
pytest_initry/protobufs/test_pb2.py
pytest_initry/protobufs/test_pb2.pyi
pytest_initry/protobufs/test_pb2_grpc.py
pytest_initry/protobufs/test_run_pb2.py
pytest_initry/protobufs/test_run_pb2.pyi
pytest_initry/protobufs/test_run_pb2_grpc.py
pytest_initry/protobufs/tests_pb2.py
pytest_initry/protobufs/tests_pb2.pyi
pytest_initry/protobufs/tests_pb2_grpc.py
pytest_initry-0.4.0.dist-info/LICENSE
pytest_initry-0.4.0.dist-info/METADATA
pytest_initry-0.4.0.dist-info/WHEEL
pytest_initry-0.4.0.dist-info/entry_points.txt
pytest_initry-0.4.0.dist-info/RECORD
