Metadata-Version: 2.1
Name: pytest-initry
Version: 0.4.0
Summary: Plugin for sending automation test data from Pytest to the initry
Home-page: https://github.com/initry/pytest-initry
License: MIT
Keywords: pytest,initry
Author: Andrejs Smirnovs
Author-email: and.inbx@gmail.com
Requires-Python: >=3.11,<4.0
Classifier: Framework :: Pytest
Classifier: License :: OSI Approved :: MIT License
Classifier: Programming Language :: Python :: 3
Classifier: Programming Language :: Python :: 3.11
Classifier: Programming Language :: Python :: 3.12
Requires-Dist: grpcio (>=1.62.1,<2.0.0)
Requires-Dist: httpx (==0.27.0)
Requires-Dist: protobuf (>=5.26.1,<6.0.0)
Requires-Dist: pytest (>=8.1.1,<9.0.0)
Project-URL: Repository, https://github.com/initry/pytest-initry
